muspy/__init__.py
muspy/base.py
muspy/classes.py
muspy/core.py
muspy/external.py
muspy/music.py
muspy/processors.py
muspy/utils.py
muspy/version.py
muspy/datasets/__init__.py
muspy/datasets/base.py
muspy/datasets/emopia.py
muspy/datasets/essen.py
muspy/datasets/haydn.py
muspy/datasets/hymnal.py
muspy/datasets/jsb.py
muspy/datasets/lmd.py
muspy/datasets/maestro.py
muspy/datasets/music21.py
muspy/datasets/musicnet.py
muspy/datasets/nes.py
muspy/datasets/nmd.py
muspy/datasets/utils.py
muspy/datasets/wikifonia.py
muspy/datasets/wrapper.py
muspy/inputs/__init__.py
muspy/inputs/abc.py
muspy/inputs/event.py
muspy/inputs/json.py
muspy/inputs/midi.py
muspy/inputs/musescore.py
muspy/inputs/music21.py
muspy/inputs/musicxml.py
muspy/inputs/note.py
muspy/inputs/pianoroll.py
muspy/inputs/pitch.py
muspy/inputs/wrappers.py
muspy/inputs/yaml.py
muspy/metrics/__init__.py
muspy/metrics/metrics.py
muspy/outputs/__init__.py
muspy/outputs/audio.py
muspy/outputs/event.py
muspy/outputs/json.py
muspy/outputs/midi.py
muspy/outputs/music21.py
muspy/outputs/musicxml.py
muspy/outputs/note.py
muspy/outputs/pianoroll.py
muspy/outputs/pitch.py
muspy/outputs/wrappers.py
muspy/outputs/yaml.py
muspy/schemas/__init__.py
muspy/schemas/utils.py
muspy/schemas/version.py
muspy/visualization/__init__.py
muspy/visualization/pianoroll.py
muspy/visualization/score.py
muspy/visualization/wrappers.py
muspy-0.5.0.dist-info/LICENSE
muspy-0.5.0.dist-info/METADATA
muspy-0.5.0.dist-info/WHEEL
muspy-0.5.0.dist-info/top_level.txt
muspy-0.5.0.dist-info/RECORD
