Metadata-Version: 2.1
Name: muspy
Version: 0.5.0
Summary: A toolkit for symbolic music generation
Home-page: https://github.com/salu133445/muspy
Author: Hao-Wen Dong
Author-email: salu.hwdong@gmail.com
License: MIT
Download-URL: https://github.com/salu133445/muspy/archive/v0.5.0.tar.gz
Project-URL: Documentation, https://salu133445.github.io/muspy/
Keywords: music,audio,music-generation,music-information-retrieval
Platform: UNKNOWN
Classifier: Development Status :: 4 - Beta
Classifier: License :: OSI Approved :: MIT License
Classifier: Programming Language :: Python :: 3
Classifier: Topic :: Multimedia :: Sound/Audio
Requires-Python: >=3.6
Requires-Dist: PyYAML (>=3.0)
Requires-Dist: bidict (>=0.21)
Requires-Dist: joblib (>=0.15)
Requires-Dist: matplotlib (>=1.5)
Requires-Dist: miditoolkit (>=0.1)
Requires-Dist: mido (>=1.0)
Requires-Dist: music21 (>=6.0)
Requires-Dist: pretty-midi (>=0.2)
Requires-Dist: pypianoroll (>=1.0)
Requires-Dist: requests (>=2.0)
Requires-Dist: tqdm (>=4.0)
Provides-Extra: dev
Requires-Dist: black (>=19.0) ; extra == 'dev'
Requires-Dist: flake8-docstrings (>=1.5) ; extra == 'dev'
Requires-Dist: flake8 (>=3.8) ; extra == 'dev'
Requires-Dist: mypy (>=0.900) ; extra == 'dev'
Requires-Dist: pylint (>=2.5) ; extra == 'dev'
Requires-Dist: sphinx-rtd-theme (>=0.5) ; extra == 'dev'
Requires-Dist: sphinx (>=3.0) ; extra == 'dev'
Provides-Extra: optional
Requires-Dist: tensorflow (>=2.0) ; extra == 'optional'
Requires-Dist: torch (>=1.0) ; extra == 'optional'
Provides-Extra: schema
Requires-Dist: jsonschema (>=3.0) ; extra == 'schema'
Requires-Dist: xmlschema (>=1.0) ; extra == 'schema'
Requires-Dist: yamale (>=2.0) ; extra == 'schema'
Provides-Extra: test
Requires-Dist: pytest (>=6.0) ; extra == 'test'
Requires-Dist: pytest-cov (>=2.0) ; extra == 'test'
